quansys/__init__.py
quansys/cli/__init__.py
quansys/cli/main.py
quansys/cli/commands/example/__init__.py
quansys/cli/commands/example/cmd.py
quansys/cli/commands/example/impl.py
quansys/cli/commands/run/__init__.py
quansys/cli/commands/run/cmd.py
quansys/cli/commands/run/impl.py
quansys/cli/commands/submit/__init__.py
quansys/cli/commands/submit/cmd.py
quansys/cli/commands/submit/impl.py
quansys/examples/__init__.py
quansys/examples/complex_config.yaml
quansys/examples/complex_design.aedt
quansys/examples/simple_config.yaml
quansys/examples/simple_design.aedt
quansys/shared/__init__.py
quansys/shared/conversion.py
quansys/shared/variables_types.py
quansys/simulation/__init__.py
quansys/simulation/base/__init__.py
quansys/simulation/base/base.py
quansys/simulation/base/base_formatters.py
quansys/simulation/base/setup_and_design_utils.py
quansys/simulation/driven_model/__init__.py
quansys/simulation/driven_model/formatter.py
quansys/simulation/driven_model/model.py
quansys/simulation/eigenmode/__init__.py
quansys/simulation/eigenmode/model.py
quansys/simulation/eigenmode/profile.py
quansys/simulation/eigenmode/results.py
quansys/simulation/quantum_epr/__init__.py
quansys/simulation/quantum_epr/distributed_analysis.py
quansys/simulation/quantum_epr/epr_calculator.py
quansys/simulation/quantum_epr/formatter.py
quansys/simulation/quantum_epr/model.py
quansys/simulation/quantum_epr/results.py
quansys/simulation/quantum_epr/run.py
quansys/simulation/quantum_epr/serializer.py
quansys/simulation/quantum_epr/structures.py
quansys/simulation/quantum_epr/modes_to_labels/__init__.py
quansys/simulation/quantum_epr/modes_to_labels/inferences.py
quansys/simulation/quantum_epr/modes_to_labels/modes_labels_scheme.py
quansys/simulation/quantum_epr/qutip_epr_simulation/__init__.py
quansys/simulation/quantum_epr/qutip_epr_simulation/composite_space.py
quansys/simulation/quantum_epr/qutip_epr_simulation/constants.py
quansys-4.0.0.dist-info/METADATA
quansys-4.0.0.dist-info/WHEEL
quansys-4.0.0.dist-info/entry_points.txt
quansys-4.0.0.dist-info/licenses/LICENSE
quansys-4.0.0.dist-info/RECORD
