Metadata-Version: 2.4
Name: quansys
Version: 4.0.0
Summary: Automated HFSS workflows for quantum circuit design and analysis
Project-URL: Homepage, https://github.com/hutorihunzu/quansys
Project-URL: Documentation, https://hutorihunzu.github.io/quansys
Project-URL: Repository, https://github.com/hutorihunzu/quansys
Project-URL: Issues, https://github.com/hutorihunzu/quansys/issues
Author-email: HutoriHunzu <uri.goldblatt@gmail.com>
License-Expression: MIT
License-File: LICENSE
Keywords: ansys,automation,circuits,electromagnetic,epr,hfss,quantum,simulation,superconducting
Classifier: Development Status :: 4 - Beta
Classifier: Intended Audience :: Science/Research
Classifier: License :: OSI Approved :: MIT License
Classifier: Operating System :: OS Independent
Classifier: Programming Language :: Python :: 3
Classifier: Programming Language :: Python :: 3.11
Classifier: Programming Language :: Python :: 3.12
Classifier: Topic :: Scientific/Engineering :: Electronic Design Automation (EDA)
Classifier: Topic :: Scientific/Engineering :: Physics
Classifier: Topic :: Software Development :: Libraries :: Python Modules
Requires-Python: >=3.11
Requires-Dist: pandas>=2.2.3
Requires-Dist: pint
Requires-Dist: pyaedt[all]==0.23.0
Requires-Dist: pycaddy
Requires-Dist: pydantic-yaml
Requires-Dist: qutip
Requires-Dist: typer
Provides-Extra: lint
Requires-Dist: ruff; extra == 'lint'
Provides-Extra: mkdocs
Requires-Dist: mkdocs; extra == 'mkdocs'
Requires-Dist: mkdocs-material; extra == 'mkdocs'
Requires-Dist: mkdocs-material-extensions; extra == 'mkdocs'
Requires-Dist: mkdocstrings; extra == 'mkdocs'
Requires-Dist: mkdocstrings-python; extra == 'mkdocs'
Requires-Dist: pymdown-extensions; extra == 'mkdocs'
Requires-Dist: ruff; extra == 'mkdocs'
Provides-Extra: test
Requires-Dist: pytest; extra == 'test'
Requires-Dist: ruff; extra == 'test'
